boptest_integration/__init__.py
boptest_integration/boptest_integration.py
boptest_integration/controllers/__init__.py
boptest_integration/controllers/controller.py
boptest_integration/controllers/pid.py
boptest_integration/controllers/pidTwoZones.py
boptest_integration/controllers/sup.py
boptest_integration/interface.py
volttron_lib_boptest_integration-0.1.1.dist-info/LICENSE
volttron_lib_boptest_integration-0.1.1.dist-info/METADATA
volttron_lib_boptest_integration-0.1.1.dist-info/WHEEL
volttron_lib_boptest_integration-0.1.1.dist-info/entry_points.txt
volttron_lib_boptest_integration-0.1.1.dist-info/RECORD
