Metadata-Version: 2.1
Name: volttron-lib-boptest-integration
Version: 0.1.1
Summary: A Volttron library for boptest simulation integration.
Home-page: https://github.com/eclipse-volttron/volttron-boptest
License: Apache-2.0
Keywords: volttron,boptest,simulation,integration
Author: Kefei Mo
Author-email: kefei.mo@pnnl.gov
Maintainer: Volttron Team
Maintainer-email: volttron@pnnl.gov
Requires-Python: >=3.10,<4.0
Classifier: Development Status :: 3 - Alpha
Classifier: Intended Audience :: Developers
Classifier: Intended Audience :: Science/Research
Classifier: License :: OSI Approved :: Apache Software License
Classifier: Programming Language :: Python :: 3
Classifier: Programming Language :: Python :: 3.10
Classifier: Programming Language :: Python :: 3.11
Classifier: Programming Language :: Python :: 3.8
Classifier: Programming Language :: Python :: 3.9
Classifier: Topic :: Home Automation
Classifier: Topic :: Software Development :: Embedded Systems
Requires-Dist: numpy (>0.0.0)
Requires-Dist: pandas (>0.0.0)
Requires-Dist: volttron (>=10.0.4rc1)
Project-URL: Bug Tracker, https://github.com/eclipse-volttron/volttron-boptest/issues
Project-URL: Repository, https://github.com/eclipse-volttron/volttron-boptest
